hctestedu_YamlTo/__init__.py
hctestedu_YamlTo/yaml_to.py
hctestedu_YamlTo/yaml_format/__init__.py
hctestedu_YamlTo/yaml_format/get_file_stream.py
hctestedu_YamlTo-0.1.dist-info/METADATA
hctestedu_YamlTo-0.1.dist-info/WHEEL
hctestedu_YamlTo-0.1.dist-info/top_level.txt
hctestedu_YamlTo-0.1.dist-info/RECORD
