Metadata-Version: 2.1
Name: hctestedu-YamlTo
Version: 0.1
Summary: 支持yaml文件里面的数据内容转化为常用的python数据
Home-page: https://github.com/pypa/sampleproject
Author: cf
Author-email: dingjun_baby@yeah.net
License: UNKNOWN
Platform: UNKNOWN
Classifier: Programming Language :: Python :: 3
Classifier: License :: OSI Approved :: MIT License
Classifier: Operating System :: OS Independent
Requires-Python: >=3.6
Requires-Dist: pyyaml
Requires-Dist: chardet
